mchplnet/__init__.py
mchplnet/examples/get_ram_example.py
mchplnet/interfaces/__init__.py
mchplnet/interfaces/abstract_interface.py
mchplnet/interfaces/can.py
mchplnet/interfaces/factory.py
mchplnet/interfaces/lin.py
mchplnet/interfaces/tcp_ip.py
mchplnet/interfaces/uart.py
mchplnet/lnet.py
mchplnet/lnetframe.py
mchplnet/services/__init__.py
mchplnet/services/frame_device_info.py
mchplnet/services/frame_getram.py
mchplnet/services/frame_load_parameter.py
mchplnet/services/frame_putram.py
mchplnet/services/frame_reboot.py
mchplnet/services/frame_save_parameter.py
mchplnet/services/scope.py
mchplnet-0.3.0.dist-info/LICENSE
mchplnet-0.3.0.dist-info/METADATA
mchplnet-0.3.0.dist-info/WHEEL
mchplnet-0.3.0.dist-info/RECORD
