Metadata-Version: 2.1
Name: mchplnet
Version: 0.3.0
Summary: Python implementation of Microchip LNet protocol
Home-page: https://x2cscope.github.io/
License: Proprietary
Author: Yash Agarwal
Classifier: License :: Other/Proprietary License
Classifier: Programming Language :: Python :: 2
Classifier: Programming Language :: Python :: 2.7
Classifier: Programming Language :: Python :: 3
Classifier: Programming Language :: Python :: 3.4
Classifier: Programming Language :: Python :: 3.5
Classifier: Programming Language :: Python :: 3.6
Classifier: Programming Language :: Python :: 3.7
Classifier: Programming Language :: Python :: 3.8
Classifier: Programming Language :: Python :: 3.9
Classifier: Programming Language :: Python :: 3.10
Classifier: Programming Language :: Python :: 3.11
Classifier: Programming Language :: Python :: 3.12
Requires-Dist: pyserial (>=3.5,<4.0)
Project-URL: Documentation, https://x2cscope.github.io/
Project-URL: Repository, https://github.com/X2Cscope/mchplnet
